anime_sama_apis/__init__.py
anime_sama_apis/catalogue.py
anime_sama_apis/episode.py
anime_sama_apis/langs.py
anime_sama_apis/scan_episode.py
anime_sama_apis/scan_season.py
anime_sama_apis/season.py
anime_sama_apis/top_level.py
anime_sama_apis/utils.py
anime_sama_apis-0.5.2.dist-info/METADATA
anime_sama_apis-0.5.2.dist-info/WHEEL
anime_sama_apis-0.5.2.dist-info/licenses/LICENSE
anime_sama_apis-0.5.2.dist-info/RECORD
