Metadata-Version: 2.4
Name: anime_sama_apis
Version: 0.5.2
Summary: Api for anime-sama.fr
Project-URL: Repository, https://github.com/Gabriel29306/anime-sama_api
Author-email: NiniKo <pcninik@gmail.com>, EvilRave <ggkervran@gmail.com>
License-Expression: GPL-3.0-or-later
License-File: LICENSE
Keywords: anime,anime-sama,downloader
Classifier: Development Status :: 4 - Beta
Classifier: Environment :: Console
Classifier: Intended Audience :: End Users/Desktop
Classifier: License :: OSI Approved :: GNU General Public License v3 or later (GPLv3+)
Classifier: Programming Language :: Python
Classifier: Programming Language :: Python :: 3.10
Classifier: Programming Language :: Python :: 3.11
Classifier: Programming Language :: Python :: 3.12
Classifier: Programming Language :: Python :: 3.13
Classifier: Topic :: Multimedia :: Video :: Capture
Classifier: Topic :: System :: Archiving
Requires-Python: >=3.10
Requires-Dist: cloudscraper>=1.2.71
